juice_trajectory_assessment/__init__.py
juice_trajectory_assessment/trajectory_assessment_comparison_report_cmd.py
juice_trajectory_assessment/trajectory_assessment_report_cmd.py
juice_trajectory_assessment/commons/__init__.py
juice_trajectory_assessment/commons/ca_event_handler.py
juice_trajectory_assessment/commons/coverage_info_handler.py
juice_trajectory_assessment/commons/mission_phases_handler.py
juice_trajectory_assessment/commons/mission_timeline_event_file_handler.py
juice_trajectory_assessment/commons/trajectory_info_handler.py
juice_trajectory_assessment/comparison_report/__init__.py
juice_trajectory_assessment/comparison_report/basic_comparison_report.py
juice_trajectory_assessment/comparison_report/comparison_report.py
juice_trajectory_assessment/comparison_report/crema.py
juice_trajectory_assessment/comparison_report/templates/custom-reference.docx
juice_trajectory_assessment/comparison_report/templates/default_a4_landscape_rst2pdf.style
juice_trajectory_assessment/comparison_report/templates/default_rst2pdf.style
juice_trajectory_assessment/report/__init__.py
juice_trajectory_assessment/report/basic_report.py
juice_trajectory_assessment/report/crema.py
juice_trajectory_assessment/report/rst_report.py
juice_trajectory_assessment/report/traj_assessment_report.py
juice_trajectory_assessment/report/templates/custom-reference.docx
juice_trajectory_assessment/report/templates/default_rst2pdf.style
test/__init__.py
test/test_ca_event_handler.py
test/test_mission_phases_handler.py
test/test_traj_assessment_report_filter.py
test/test_trajectory_report_e2e.py
juice_trajectory_assessment-0.7.1.dist-info/METADATA
juice_trajectory_assessment-0.7.1.dist-info/WHEEL
juice_trajectory_assessment-0.7.1.dist-info/entry_points.txt
juice_trajectory_assessment-0.7.1.dist-info/top_level.txt
juice_trajectory_assessment-0.7.1.dist-info/RECORD
