Metadata-Version: 2.4
Name: juice_trajectory_assessment
Version: 0.7.1
Summary: Python package for reporting Juice Trajectory Assessment
Home-page: https://juigitlab.esac.esa.int/core-system/uplink/juice_trajectory_assessment
Author: JUICE SOC team
Author-email: juice_soc@cosmos.esa.int
Keywords: esa,Juice,EPS,OSVE,planetary,space,metrics,trajectory,assessment,crema
Classifier: Development Status :: 4 - Beta
Classifier: Intended Audience :: Science/Research
Classifier: Topic :: Scientific/Engineering :: Astronomy
Classifier: Programming Language :: Python :: 3.7
Requires-Dist: tabulate>=0.9.0
Requires-Dist: esac-juice-pyutils>=0.3.2
Requires-Dist: osve_wrapper>=0.2.5
Requires-Dist: soa-report>=1.2.0
Requires-Dist: rst2html5>=2.0
Dynamic: author
Dynamic: author-email
Dynamic: classifier
Dynamic: description
Dynamic: description-content-type
Dynamic: home-page
Dynamic: keywords
Dynamic: requires-dist
Dynamic: summary
